roaringrel/__init__.py
roaringrel/py.typed
roaringrel-1.0.0.post2.dist-info/METADATA
roaringrel-1.0.0.post2.dist-info/WHEEL
roaringrel-1.0.0.post2.dist-info/licenses/LICENSE
roaringrel-1.0.0.post2.dist-info/RECORD
