Metadata-Version: 2.3
Name: roaringrel
Version: 1.0.0.post2
Summary: Implementation of integer relations based on roaring bitmaps.
Project-URL: Documentation, https://roaringrel.readthedocs.io
Project-URL: Repository, https://github.com/hashberg-io/roaringrel
Project-URL: Issues, https://github.com/hashberg-io/roaringrel/issues
Author: Hashberg
License: LGPL-3.0
Classifier: Development Status :: 4 - Beta
Classifier: Natural Language :: English
Classifier: Operating System :: OS Independent
Classifier: Programming Language :: Python :: 3
Classifier: Programming Language :: Python :: 3.13
Classifier: Programming Language :: Python :: 3.14
Classifier: Typing :: Typed
Requires-Python: >=3.13
Requires-Dist: pyroaring>=1.0.3
